doculib/__init__.py
doculib/report.py
doculib/primitives/base.css
doculib/primitives/cortex.png
doculib/primitives/footer.j2
doculib/primitives/header.j2
doculib/primitives/html_head.j2
doculib/primitives/icon-alert.svg
doculib/primitives/icon-cancel.svg
doculib/primitives/icon-checkmark.svg
doculib/primitives/icon-notify.svg
doculib/primitives/icon-unchecked.svg
doculib/primitives/logo.png
doculib/primitives/prisma.png
doculib/primitives/section_head.j2
doculib/primitives/stats_block.j2
doculib/primitives/strata.png
doculib/primitives/table.j2
doculib/primitives/title.j2
doculib-0.0.0.3.dist-info/LICENSE
doculib-0.0.0.3.dist-info/METADATA
doculib-0.0.0.3.dist-info/WHEEL
doculib-0.0.0.3.dist-info/top_level.txt
doculib-0.0.0.3.dist-info/RECORD
